{
  "title": "Alerta en 'cinturón verde de Boyacá' tras asalto a mina esmeraldera de Maripí: comando armado de 34 hombres buscaba valiosas piedras de yacimiento",
  "text": "El violento asalto se registró en la Mina Cunas, propiedad de la empresa Esmeraldas Santa Rosa.",
  "publish_date": "2025-12-14T12:14:36-05:00",
  "source": "https://www.eltiempo.com/rss/colombia.xml",
  "link": "https://www.eltiempo.com/colombia/otras-ciudades/alerta-en-el-cinturon-verde-de-boyaca-tras-asalto-armado-a-mina-esmeraldera-de-maripi-comando-armado-de-34-hombres-irrumpio-en-yacimiento-3516772",
  "processed_at": "2025-12-15T16:44:45.081702"
}