{
  "title": "¡Que viva El Congo Grande! la danza de Barranquilla que celebra 150 años con izada de bandera y ritual ancestral",
  "text": "La danza más antigua del Carnaval celebra este sábado en el barrio Los Andes y se declara lista para el Carnaval de Barranquilla 2026.",
  "publish_date": "2025-12-20T10:24:47-05:00",
  "source": "https://www.eltiempo.com/rss/colombia.xml",
  "link": "https://www.eltiempo.com/colombia/barranquilla/congo-grande-de-barranquilla-celebra-150-anos-con-izada-de-bandera-y-ritual-ancestral-3518545",
  "processed_at": "2025-12-20T18:31:44.976529"
}